{
  "entity": "TourDayActivityEntity",
  "template": {
    "Id": null,
    "CreatedOnUtc": null,
    "CreatedBy": null,
    "LastModifiedOnUtc": null,
    "LastModifiedBy": null,
    "TourDayId": null,
    "TourDay": null,
    "Order": null,
    "ActivityType": null,
    "Title": null,
    "Description": null,
    "Note": null,
    "EstimatedCost": null,
    "IsOptional": null,
    "Translations": {},
    "StartTime": null,
    "EndTime": null,
    "Routes": [],
    "Accommodation": null
  },
  "types": {
    "Id": "Guid",
    "CreatedOnUtc": "DateTimeOffset",
    "CreatedBy": "string?",
    "LastModifiedOnUtc": "DateTimeOffset?",
    "LastModifiedBy": "string?",
    "TourDayId": "Guid",
    "TourDay": "TourDayEntity",
    "Order": "int",
    "ActivityType": "TourDayActivityType",
    "Title": "string",
    "Description": "string?",
    "Note": "string?",
    "EstimatedCost": "decimal?",
    "IsOptional": "bool",
    "Translations": "Dictionary<string, TourDayActivityTranslationData>",
    "StartTime": "TimeOnly?",
    "EndTime": "TimeOnly?",
    "Routes": "List<TourPlanRouteEntity>",
    "Accommodation": "TourPlanAccommodationEntity?"
  },
  "data": []
}
